repoch_client/__init__.py
repoch_client-0.0.1.dist-info/METADATA
repoch_client-0.0.1.dist-info/WHEEL
repoch_client-0.0.1.dist-info/top_level.txt
repoch_client-0.0.1.dist-info/RECORD
