Metadata-Version: 2.4
Name: repoch-client
Version: 0.0.1
Summary: Under development
Classifier: Development Status :: 1 - Planning
Classifier: Intended Audience :: Developers
Classifier: Programming Language :: Python :: 3
Requires-Python: >=3.7
